RTL/Generic_Timer.v
/*
    Author: Moaz Mohamed
    Description: This is the source verilog code describing a parametrized timer that ticks every specific time. 
                 the tick time depends on the Final Value which is fed into the module. 
*/

module Timer #(parameter TIMER_BITS=4)(
    input wire clk,
    input wire reset,
    input wire enable,
    input wire [TIMER_BITS-1:0] Final_Value,
    output reg tick
);
    
    /*Define a register with the specified number of bit width*/
    reg [TIMER_BITS-1:0] Q_reg,Q_next;
    
    /*Sequential always block*/
    always @(posedge clk, negedge reset) begin
        if(~reset)
        begin
            Q_reg<='b0;
        end
        else if (enable)
        begin
            Q_reg<=Q_next;
        end
        else
        begin
            Q_reg<=Q_reg;
        end
    end

    /*Combinational Output*/
    always @(*) begin
        if (Q_reg == Final_Value) begin
            tick=1'b1;
        end
        else
        begin
            tick=1'b0;
        end
    end

    /*Next state logic*/
    always @(*) begin
        if(tick == 1'b1)
        begin
            Q_next='b0;
        end
        else
        begin
            Q_next=Q_reg+1'b1;
        end
    end
    
endmodule

RTL/PWM.v
/*
    Author: Moaz Mohamed
    Description: This is the source Verilog code of the top module that describes the PWM Generator.
*/
`include "Generic_Timer.v"
module PWM #(parameter BITS = 8,TIMER_BITS = 8)(
    input wire clk,
    input wire reset,
    input wire [TIMER_BITS-1:0]Final_Value,
    input wire [BITS:0] duty,
    output reg pwm_out
);
    
    /*Internal Signals*/
    wire counter_en;
    
    /*Counter Value*/
    reg [BITS-1:0] count_reg,count_next;

    /*PWM outputs*/
    reg pwm_next,pwm_reg;

    /*Timer Instance*/
    Timer #(.TIMER_BITS(TIMER_BITS)) U1(
        .clk(clk),
        .reset(reset),
        .enable(1'b1),
        .Final_Value(Final_Value),
        .tick(counter_en)
    );

    /*Sequential block*/
    always @(posedge clk, negedge reset) begin
        if (~reset) begin
            count_reg<='b0;
        end
        else if(counter_en)
        begin
            count_reg<=count_next;
            pwm_reg<=pwm_next;
        end
        else
        begin
            count_reg<=count_reg;
            pwm_reg<=pwm_reg;
        end
    end

    /*PWM next state logic*/
    always @(*) begin
        if (count_reg < duty) begin
            pwm_next=1'b1;
        end
        else
        begin
            pwm_next=1'b0;
        end
    end

    /*Up counter next state logic*/
    always @(*) begin
        count_next=count_reg+1'b1;
    end

    /*PWM Output logic*/
    always @(*) begin
        pwm_out=pwm_reg;
    end

endmodule

Testing/Testbench/PWM_tb.v
/*
    Author: Moaz Mohamed
    Description: Testbench for the PWM Generator.
*/

/*time scale unit = 1ns with resolution=0.1ns*/
`timescale 1ns/100ps

module PWM_tb ();

    /*Test Signals*/
    reg clk_tb;
    reg reset_tb;
    reg [7:0] Final_Value_tb;
    reg [8:0] duty_tb;
    wire pwm_out_tb;
    /*Module instance*/
    PWM DUT(
        .clk(clk_tb),
        .reset(reset_tb),
        .Final_Value(Final_Value_tb),
        .duty(duty_tb),
        .pwm_out(pwm_out_tb)
    );
    
    /*Clock Generator with period 1ns*/
    always #0.5 clk_tb=~clk_tb;

    /*Initial block*/
    initial begin
        $dumpfile("PWM.vcd");
        $dumpvars;
        /*Reset*/
        clk_tb=1'b0;
        reset_tb=1'b0;
        Final_Value_tb='d3; //with switching freq of approximately 1MHz
        duty_tb='d64; //this should generate 0.25 duty

        #1
        reset_tb=1'b1;

        #30000;
        $stop;
    end
endmodule

Testing/Modelsim results/PWM.vcd
$date
	Mon Jul 24 18:02:17 2023
$end
$version
	ModelSim Version 10.5
$end
$timescale
	100ps
$end

$scope module PWM_tb $end
$var reg 1 ! clk_tb $end
$var reg 1 " reset_tb $end
$var reg 8 # Final_Value_tb [7:0] $end
$var reg 9 $ duty_tb [8:0] $end
$var wire 1 % pwm_out_tb $end

$scope module DUT $end
$var parameter 32 & BITS $end
$var parameter 32 ' TIMER_BITS $end
$var wire 1 ( clk $end
$var wire 1 ) reset $end
$var wire 1 * Final_Value [7] $end
$var wire 1 + Final_Value [6] $end
$var wire 1 , Final_Value [5] $end
$var wire 1 - Final_Value [4] $end
$var wire 1 . Final_Value [3] $end
$var wire 1 / Final_Value [2] $end
$var wire 1 0 Final_Value [1] $end
$var wire 1 1 Final_Value [0] $end
$var wire 1 2 duty [8] $end
$var wire 1 3 duty [7] $end
$var wire 1 4 duty [6] $end
$var wire 1 5 duty [5] $end
$var wire 1 6 duty [4] $end
$var wire 1 7 duty [3] $end
$var wire 1 8 duty [2] $end
$var wire 1 9 duty [1] $end
$var wire 1 : duty [0] $end
$var reg 1 ; pwm_out $end
$var wire 1 < counter_en $end
$var reg 8 = count_reg [7:0] $end
$var reg 8 > count_next [7:0] $end
$var reg 1 ? pwm_next $end
$var reg 1 @ pwm_reg $end

$scope module U1 $end
$var parameter 32 A TIMER_BITS $end
$var wire 1 ( clk $end
$var wire 1 ) reset $end
$var wire 1 B enable $end
$var wire 1 * Final_Value [7] $end
$var wire 1 + Final_Value [6] $end
$var wire 1 , Final_Value [5] $end
$var wire 1 - Final_Value [4] $end
$var wire 1 . Final_Value [3] $end
$var wire 1 / Final_Value [2] $end
$var wire 1 0 Final_Value [1] $end
$var wire 1 1 Final_Value [0] $end
$var reg 1 C tick $end
$var reg 8 D Q_reg [7:0] $end
$var reg 8 E Q_next [7:0] $end
$upscope $end
$upscope $end
$upscope $end
$enddefinitions $end
#0
$dumpvars
0!
0"
b11 #
b1000000 $
x;
b0 =
b1 >
1?
x@
0C
b0 D
b1 E
b1000 &
b1000 '
b1000 A
x%
0<
0:
09
08
07
06
05
14
03
02
11
10
0/
0.
0-
0,
0+
0*
0)
0(
1B
$end
#5
1!
1(
#10
1"
0!
1)
0(
#15
1!
1(
b1 D
b10 E
#20
0!
0(
#25
1!
1(
b10 D
b11 E
#30
0!
0(
#35
1!
1(
b11 D
1C
b0 E
1<
#40
0!
0(
#45
1!
1(
b1 =
1@
b0 D
0C
b1 E
1;
b10 >
0<
1%
#50
0!
0(
#55
1!
1(
b1 D
b10 E
#60
0!
0(
#65
1!
1(
b10 D
b11 E
#70
0!
0(
#75
1!
1(
b11 D
1C
b0 E
1<
#80
0!
0(
#85
1!
1(
b10 =
b0 D
0C
b1 E
b11 >
0<
#90
0!
0(
#95
1!
1(
b1 D
b10 E
#100
0!
0(
#105
1!
1(
b10 D
b11 E
#110
0!
0(
#115
1!
1(
b11 D
1C
b0 E
1<
#120
0!
0(
#125
1!
1(
b11 =
b0 D
0C
b1 E
b100 >
0<
#130
0!
0(
#135
1!
1(
b1 D
b10 E
#140
0!
0(
#145
1!
1(
b10 D
b11 E
#150
0!
0(
#155
1!
1(
b11 D
1C
b0 E
1<
#160
0!
0(
#165
1!
1(
b100 =
b0 D
0C
b1 E
b101 >
0<
#170
0!
0(
#175
1!
1(
b1 D
b10 E
#180
0!
0(
#185
1!
1(
b10 D
b11 E
#190
0!
0(
#195
1!
1(
b11 D
1C
b0 E
1<
#200
0!
0(
#205
1!
1(
b101 =
b0 D
0C
b1 E
b110 >
0<
#210
0!
0(
#215
1!
1(
b1 D
b10 E
#220
0!
0(
#225
1!
1(
b10 D
b11 E
#230
0!
0(
#235
1!
1(
b11 D
1C
b0 E
1<
#240
0!
0(
#245
1!
1(
b110 =
b0 D
0C
b1 E
b111 >
0<
#250
0!
0(
#255
1!
1(
b1 D
b10 E
#260
0!
0(
#265
1!
1(
b10 D
b11 E
#270
0!
0(
#275
1!
1(
b11 D
1C
b0 E
1<
#280
0!
0(
#285
1!
1(
b111 =
b0 D
0C
b1 E
b1000 >
0<
#290
0!
0(
#295
1!
1(
b1 D
b10 E
#300
0!
0(
#305
1!
1(
b10 D
b11 E
#310
0!
0(
#315
1!
1(
b11 D
1C
b0 E
1<
#320
0!
0(
#325
1!
1(
b1000 =
b0 D
0C
b1 E
b1001 >
0<
#330
0!
0(
#335
1!
1(
b1 D
b10 E
#340
0!
0(
#345
1!
1(
b10 D
b11 E
#350
0!
0(
#355
1!
1(
b11 D
1C
b0 E
1<
#360
0!
0(
#365
1!
1(
b1001 =
b0 D
0C
b1 E
b1010 >
0<
#370
0!
0(
#375
1!
1(
b1 D
b10 E
#380
0!
0(
#385
1!
1(
b10 D
b11 E
#390
0!
0(
#395
1!
1(
b11 D
1C
b0 E
1<
#400
0!
0(
#405
1!
1(
b1010 =
b0 D
0C
b1 E
b1011 >
0<
#410
0!
0(
#415
1!
1(
b1 D
b10 E
#420
0!
0(
#425
1!
1(
b10 D
b11 E
#430
0!
0(
#435
1!
1(
b11 D
1C
b0 E
1<
#440
0!
0(
#445
1!
1(
b1011 =
b0 D
0C
b1 E
b1100 >
0<
#450
0!
0(
#455
1!
1(
b1 D
b10 E
#460
0!
0(
#465
1!
1(
b10 D
b11 E
#470
0!
0(
#475
1!
1(
b11 D
1C
b0 E
1<
#480
0!
0(
#485
1!
1(
b1100 =
b0 D
0C
b1 E
b1101 >
0<
#490
0!
0(
#495
1!
1(
b1 D
b10 E
#500
0!
0(
#505
1!
1(
b10 D
b11 E
#510
0!
0(
#515
1!
1(
b11 D
1C
b0 E
1<
#520
0!
0(
#525
1!
1(
b1101 =
b0 D
0C
b1 E
b1110 >
0<
#530
0!
0(
#535
1!
1(
b1 D
b10 E
#540
0!
0(
#545
1!
1(
b10 D
b11 E
#550
0!
0(
#555
1!
1(
b11 D
1C
b0 E
1<
#560
0!
0(
#565
1!
1(
b1110 =
b0 D
0C
b1 E
b1111 >
0<
#570
0!
0(
#575
1!
1(
b1 D
b10 E
#580
0!
0(
#585
1!
1(
b10 D
b11 E
#590
0!
0(
#595
1!
1(
b11 D
1C
b0 E
1<
#600
0!
0(
#605
1!
1(
b1111 =
b0 D
0C
b1 E
b10000 >
0<
#610
0!
0(
#615
1!
1(
b1 D
b10 E
#620
0!
0(
#625
1!
1(
b10 D
b11 E
#630
0!
0(
#635
1!
1(
b11 D
1C
b0 E
1<
#640
0!
0(
#645
1!
1(
b10000 =
b0 D
0C
b1 E
b10001 >
0<
#650
0!
0(
#655
1!
1(
b1 D
b10 E
#660
0!
0(
#665
1!
1(
b10 D
b11 E
#670
0!
0(
#675
1!
1(
b11 D
1C
b0 E
1<
#680
0!
0(
#685
1!
1(
b10001 =
b0 D
0C
b1 E
b10010 >
0<
#690
0!
0(
#695
1!
1(
b1 D
b10 E
#700
0!
0(
#705
1!
1(
b10 D
b11 E
#710
0!
0(
#715
1!
1(
b11 D
1C
b0 E
1<
#720
0!
0(
#725
1!
1(
b10010 =
b0 D
0C
b1 E
b10011 >
0<
#730
0!
0(
#735
1!
1(
b1 D
b10 E
#740
0!
0(
#745
1!
1(
b10 D
b11 E
#750
0!
0(
#755
1!
1(
b11 D
1C
b0 E
1<
#760
0!
0(
#765
1!
1(
b10011 =
b0 D
0C
b1 E
b10100 >
0<
#770
0!
0(
#775
1!
1(
b1 D
b10 E
#780
0!
0(
#785
1!
1(
b10 D
b11 E
#790
0!
0(
#795
1!
1(
b11 D
1C
b0 E
1<
#800
0!
0(
#805
1!
1(
b10100 =
b0 D
0C
b1 E
b10101 >
0<
#810
0!
0(
#815
1!
1(
b1 D
b10 E
#820
0!
0(
#825
1!
1(
b10 D
b11 E
#830
0!
0(
#835
1!
1(
b11 D
1C
b0 E
1<
#840
0!
0(
#845
1!
1(
b10101 =
b0 D
0C
b1 E
b10110 >
0<
#850
0!
0(
#855
1!
1(
b1 D
b10 E
#860
0!
0(
#865
1!
1(
b10 D
b11 E
#870
0!
0(
#875
1!
1(
b11 D
1C
b0 E
1<
#880
0!
0(
#885
1!
1(
b10110 =
b0 D
0C
b1 E
b10111 >
0<
#890
0!
0(
#895
1!
1(
b1 D
b10 E
#900
0!
0(
#905
1!
1(
b10 D
b11 E
#910
0!
0(
#915
1!
1(
b11 D
1C
b0 E
1<
#920
0!
0(
#925
1!
1(
b10111 =
b0 D
0C
b1 E
b11000 >
0<
#930
0!
0(
#935
1!
1(
b1 D
b10 E
#940
0!
0(
#945
1!
1(
b10 D
b11 E
#950
0!
0(
#955
1!
1(
b11 D
1C
b0 E
1<
#960
0!
0(
#965
1!
1(
b11000 =
b0 D
0C
b1 E
b11001 >
0<
#970
0!
0(
#975
1!
1(
b1 D
b10 E
#980
0!
0(
#985
1!
1(
b10 D
b11 E
#990
0!
0(
#995
1!
1(
b11 D
1C
b0 E
1<
#1000
0!
0(
#1005
1!
1(
b11001 =
b0 D
0C
b1 E
b11010 >
0<
#1010
0!
0(
#1015
1!
1(
b1 D
b10 E
#1020
0!
0(
#1025
1!
1(
b10 D
b11 E
#1030
0!
0(
#1035
1!
1(
b11 D
1C
b0 E
1<
#1040
0!
0(
#1045
1!
1(
b11010 =
b0 D
0C
b1 E
b11011 >
0<
#1050
0!
0(
#1055
1!
1(
b1 D
b10 E
#1060
0!
0(
#1065
1!
1(
b10 D
b11 E
#1070
0!
0(
#1075
1!
1(
b11 D
1C
b0 E
1<
#1080
0!
0(
#1085
1!
1(
b11011 =
b0 D
0C
b1 E
b11100 >
0<
#1090
0!
0(
#1095
1!
1(
b1 D
b10 E
#1100
0!
0(
#1105
1!
1(
b10 D
b11 E
#1110
0!
0(
#1115
1!
1(
b11 D
1C
b0 E
1<
#1120
0!
0(
#1125
1!
1(
b11100 =
b0 D
0C
b1 E
b11101 >
0<
#1130
0!
0(
#1135
1!
1(
b1 D
b10 E
#1140
0!
0(
#1145
1!
1(
b10 D
b11 E
#1150
0!
0(
#1155
1!
1(
b11 D
1C
b0 E
1<
#1160
0!
0(
#1165
1!
1(
b11101 =
b0 D
0C
b1 E
b11110 >
0<
#1170
0!
0(
#1175
1!
1(
b1 D
b10 E
#1180
0!
0(
#1185
1!
1(
b10 D
b11 E
#1190
0!
0(
#1195
1!
1(
b11 D
1C
b0 E
1<
#1200
0!
0(
#1205
1!
1(
b11110 =
b0 D
0C
b1 E
b11111 >
0<
#1210
0!
0(
#1215
1!
1(
b1 D
b10 E
#1220
0!
0(
#1225
1!
1(
b10 D
b11 E
#1230
0!
0(
#1235
1!
1(
b11 D
1C
b0 E
1<
#1240
0!
0(
#1245
1!
1(
b11111 =
b0 D
0C
b1 E
b100000 >
0<
#1250
0!
0(
#1255
1!
1(
b1 D
b10 E
#1260
0!
0(
#1265
1!
1(
b10 D
b11 E
#1270
0!
0(
#1275
1!
1(
b11 D
1C
b0 E
1<
#1280
0!
0(
#1285
1!
1(
b100000 =
b0 D
0C
b1 E
b100001 >
0<
#1290
0!
0(
#1295
1!
1(
b1 D
b10 E
#1300
0!
0(
#1305
1!
1(
b10 D
b11 E
#1310
0!
0(
#1315
1!
1(
b11 D
1C
b0 E
1<
#1320
0!
0(
#1325
1!
1(
b100001 =
b0 D
0C
b1 E
b100010 >
0<
#1330
0!
0(
#1335
1!
1(
b1 D
b10 E
#1340
0!
0(
#1345
1!
1(
b10 D
b11 E
#1350
0!
0(
#1355
1!
1(
b11 D
1C
b0 E
1<
#1360
0!
0(
#1365
1!
1(
b100010 =
b0 D
0C
b1 E
b100011 >
0<
#1370
0!
0(
#1375
1!
1(
b1 D
b10 E
#1380
0!
0(
#1385
1!
1(
b10 D
b11 E
#1390
0!
0(
#1395
1!
1(
b11 D
1C
b0 E
1<
#1400
0!
0(
#1405
1!
1(
b100011 =
b0 D
0C
b1 E
b100100 >
0<
#1410
0!
0(
#1415
1!
1(
b1 D
b10 E
#1420
0!
0(
#1425
1!
1(
b10 D
b11 E
#1430
0!
0(
#1435
1!
1(
b11 D
1C
b0 E
1<
#1440
0!
0(
#1445
1!
1(
b100100 =
b0 D
0C
b1 E
b100101 >
0<
#1450
0!
0(
#1455
1!
1(
b1 D
b10 E
#1460
0!
0(
#1465
1!
1(
b10 D
b11 E
#1470
0!
0(
#1475
1!
1(
b11 D
1C
b0 E
1<
#1480
0!
0(
#1485
1!
1(
b100101 =
b0 D
0C
b1 E
b100110 >
0<
#1490
0!
0(
#1495
1!
1(
b1 D
b10 E
#1500
0!
0(
#1505
1!
1(
b10 D
b11 E
#1510
0!
0(
#1515
1!
1(
b11 D
1C
b0 E
1<
#1520
0!
0(
#1525
1!
1(
b100110 =
b0 D
0C
b1 E
b100111 >
0<
#1530
0!
0(
#1535
1!
1(
b1 D
b10 E
#1540
0!
0(
#1545
1!
1(
b10 D
b11 E
#1550
0!
0(
#1555
1!
1(
b11 D
1C
b0 E
1<
#1560
0!
0(
#1565
1!
1(
b100111 =
b0 D
0C
b1 E
b101000 >
0<
#1570
0!
0(
#1575
1!
1(
b1 D
b10 E
#1580
0!
0(
#1585
1!
1(
b10 D
b11 E
#1590
0!
0(
#1595
1!
1(
b11 D
1C
b0 E
1<
#1600
0!
0(
#1605
1!
1(
b101000 =
b0 D
0C
b1 E
b101001 >
0<
#1610
0!
0(
#1615
1!
1(
b1 D
b10 E
#1620
0!
0(
#1625
1!
1(
b10 D
b11 E
#1630
0!
0(
#1635
1!
1(
b11 D
1C
b0 E
1<
#1640
0!
0(
#1645
1!
1(
b101001 =
b0 D
0C
b1 E
b101010 >
0<
#1650
0!
0(
#1655
1!
1(
b1 D
b10 E
#1660
0!
0(
#1665
1!
1(
b10 D
b11 E
#1670
0!
0(
#1675
1!
1(
b11 D
1C
b0 E
1<
#1680
0!
0(
#1685
1!
1(
b101010 =
b0 D
0C
b1 E
b101011 >
0<
#1690
0!
0(
#1695
1!
1(
b1 D
b10 E
#1700
0!
0(
#1705
1!
1(
b10 D
b11 E
#1710
0!
0(
#1715
1!
1(
b11 D
1C
b0 E
1<
#1720
0!
0(
#1725
1!
1(
b101011 =
b0 D
0C
b1 E
b101100 >
0<
#1730
0!
0(
#1735
1!
1(
b1 D
b10 E
#1740
0!
0(
#1745
1!
1(
b10 D
b11 E
#1750
0!
0(
#1755
1!
1(
b11 D
1C
b0 E
1<
#1760
0!
0(
#1765
1!
1(
b101100 =
b0 D
0C
b1 E
b101101 >
0<
#1770
0!
0(
#1775
1!
1(
b1 D
b10 E
#1780
0!
0(
#1785
1!
1(
b10 D
b11 E
#1790
0!
0(
#1795
1!
1(
b11 D
1C
b0 E
1<
#1800
0!
0(
#1805
1!
1(
b101101 =
b0 D
0C
b1 E
b101110 >
0<
#1810
0!
0(
#1815
1!
1(
b1 D
b10 E
#1820
0!
0(
#1825
1!
1(
b10 D
b11 E
#1830
0!
0(
#1835
1!
1(
b11 D
1C
b0 E
1<
#1840
0!
0(
#1845
1!
1(
b101110 =
b0 D
0C
b1 E
b101111 >
0<
#1850
0!
0(
#1855
1!
1(
b1 D
b10 E
#1860
0!
0(
#1865
1!
1(
b10 D
b11 E
#1870
0!
0(
#1875
1!
1(
b11 D
1C
b0 E
1<
#1880
0!
0(
#1885
1!
1(
b101111 =
b0 D
0C
b1 E
b110000 >
0<
#1890
0!
0(
#1895
1!
1(
b1 D
b10 E
#1900
0!
0(
#1905
1!
1(
b10 D
b11 E
#1910
0!
0(
#1915
1!
1(
b11 D
1C
b0 E
1<
#1920
0!
0(
#1925
1!
1(
b110000 =
b0 D
0C
b1 E
b110001 >
0<
#1930
0!
0(
#1935
1!
1(
b1 D
b10 E
#1940
0!
0(
#1945
1!
1(
b10 D
b11 E
#1950
0!
0(
#1955
1!
1(
b11 D
1C
b0 E
1<
#1960
0!
0(
#1965
1!
1(
b110001 =
b0 D
0C
b1 E
b110010 >
0<
#1970
0!
0(
#1975
1!
1(
b1 D
b10 E
#1980
0!
0(
#1985
1!
1(
b10 D
b11 E
#1990
0!
0(
#1995
1!
1(
b11 D
1C
b0 E
1<
#2000
0!
0(
#2005
1!
1(
b110010 =
b0 D
0C
b1 E
b110011 >
0<
#2010
0!
0(
#2015
1!
1(
b1 D
b10 E
#2020
0!
0(
#2025
1!
1(
b10 D
b11 E
#2030
0!
0(
#2035
1!
1(
b11 D
1C
b0 E
1<
#2040
0!
0(
#2045
1!
1(
b110011 =
b0 D
0C
b1 E
b110100 >
0<
#2050
0!
0(
#2055
1!
1(
b1 D
b10 E
#2060
0!
0(
#2065
1!
1(
b10 D
b11 E
#2070
0!
0(
#2075
1!
1(
b11 D
1C
b0 E
1<
#2080
0!
0(
#2085
1!
1(
b110100 =
b0 D
0C
b1 E
b110101 >
0<
#2090
0!
0(
#2095
1!
1(
b1 D
b10 E
#2100
0!
0(
#2105
1!
1(
b10 D
b11 E
#2110
0!
0(
#2115
1!
1(
b11 D
1C
b0 E
1<
#2120
0!
0(
#2125
1!
1(
b110101 =
b0 D
0C
b1 E
b110110 >
0<
#2130
0!
0(
#2135
1!
1(
b1 D
b10 E
#2140
0!
0(
#2145
1!
1(
b10 D
b11 E
#2150
0!
0(
#2155
1!
1(
b11 D
1C
b0 E
1<
#2160
0!
0(
#2165
1!
1(
b110110 =
b0 D
0C
b1 E
b110111 >
0<
#2170
0!
0(
#2175
1!
1(
b1 D
b10 E
#2180
0!
0(
#2185
1!
1(
b10 D
b11 E
#2190
0!
0(
#2195
1!
1(
b11 D
1C
b0 E
1<
#2200
0!
0(
#2205
1!
1(
b110111 =
b0 D
0C
b1 E
b111000 >
0<
#2210
0!
0(
#2215
1!
1(
b1 D
b10 E
#2220
0!
0(
#2225
1!
1(
b10 D
b11 E
#2230
0!
0(
#2235
1!
1(
b11 D
1C
b0 E
1<
#2240
0!
0(
#2245
1!
1(
b111000 =
b0 D
0C
b1 E
b111001 >
0<
#2250
0!
0(
#2255
1!
1(
b1 D
b10 E
#2260
0!
0(
#2265
1!
1(
b10 D
b11 E
#2270
0!
0(
#2275
1!
1(
b11 D
1C
b0 E
1<
#2280
0!
0(
#2285
1!
1(
b111001 =
b0 D
0C
b1 E
b111010 >
0<
#2290
0!
0(
#2295
1!
1(
b1 D
b10 E
#2300
0!
0(
#2305
1!
1(
b10 D
b11 E
#2310
0!
0(
#2315
1!
1(
b11 D
1C
b0 E
1<
#2320
0!
0(
#2325
1!
1(
b111010 =
b0 D
0C
b1 E
b111011 >
0<
#2330
0!
0(
#2335
1!
1(
b1 D
b10 E
#2340
0!
0(
#2345
1!
1(
b10 D
b11 E
#2350
0!
0(
#2355
1!
1(
b11 D
1C
b0 E
1<
#2360
0!
0(
#2365
1!
1(
b111011 =
b0 D
0C
b1 E
b111100 >
0<
#2370
0!
0(
#2375
1!
1(
b1 D
b10 E
#2380
0!
0(
#2385
1!
1(
b10 D
b11 E
#2390
0!
0(
#2395
1!
1(
b11 D
1C
b0 E
1<
#2400
0!
0(
#2405
1!
1(
b111100 =
b0 D
0C
b1 E
b111101 >
0<
#2410
0!
0(
#2415
1!
1(
b1 D
b10 E
#2420
0!
0(
#2425
1!
1(
b10 D
b11 E
#2430
0!
0(
#2435
1!
1(
b11 D
1C
b0 E
1<
#2440
0!
0(
#2445
1!
1(
b111101 =
b0 D
0C
b1 E
b111110 >
0<
#2450
0!
0(
#2455
1!
1(
b1 D
b10 E
#2460
0!
0(
#2465
1!
1(
b10 D
b11 E
#2470
0!
0(
#2475
1!
1(
b11 D
1C
b0 E
1<
#2480
0!
0(
#2485
1!
1(
b111110 =
b0 D
0C
b1 E
b111111 >
0<
#2490
0!
0(
#2495
1!
1(
b1 D
b10 E
#2500
0!
0(
#2505
1!
1(
b10 D
b11 E
#2510
0!
0(
#2515
1!
1(
b11 D
1C
b0 E
1<
#2520
0!
0(
#2525
1!
1(
b111111 =
b0 D
0C
b1 E
b1000000 >
0<
#2530
0!
0(
#2535
1!
1(
b1 D
b10 E
#2540
0!
0(
#2545
1!
1(
b10 D
b11 E
#2550
0!
0(
#2555
1!
1(
b11 D
1C
b0 E
1<
#2560
0!
0(
#2565
1!
1(
b1000000 =
b0 D
0C
b1 E
0?
b1000001 >
0<
#2570
0!
0(
#2575
1!
1(
b1 D
b10 E
#2580
0!
0(
#2585
1!
1(
b10 D
b11 E
#2590
0!
0(
#2595
1!
1(
b11 D
1C
b0 E
1<
#2600
0!
0(
#2605
1!
1(
b1000001 =
0@
b0 D
0C
b1 E
0;
b1000010 >
0<
0%
#2610
0!
0(
#2615
1!
1(
b1 D
b10 E
#2620
0!
0(
#2625
1!
1(
b10 D
b11 E
#2630
0!
0(
#2635
1!
1(
b11 D
1C
b0 E
1<
#2640
0!
0(
#2645
1!
1(
b1000010 =
b0 D
0C
b1 E
b1000011 >
0<
#2650
0!
0(
#2655
1!
1(
b1 D
b10 E
#2660
0!
0(
#2665
1!
1(
b10 D
b11 E
#2670
0!
0(
#2675
1!
1(
b11 D
1C
b0 E
1<
#2680
0!
0(
#2685
1!
1(
b1000011 =
b0 D
0C
b1 E
b1000100 >
0<
#2690
0!
0(
#2695
1!
1(
b1 D
b10 E
#2700
0!
0(
#2705
1!
1(
b10 D
b11 E
#2710
0!
0(
#2715
1!
1(
b11 D
1C
b0 E
1<
#2720
0!
0(
#2725
1!
1(
b1000100 =
b0 D
0C
b1 E
b1000101 >
0<
#2730
0!
0(
#2735
1!
1(
b1 D
b10 E
#2740
0!
0(
#2745
1!
1(
b10 D
b11 E
#2750
0!
0(
#2755
1!
1(
b11 D
1C
b0 E
1<
#2760
0!
0(
#2765
1!
1(
b1000101 =
b0 D
0C
b1 E
b1000110 >
0<
#2770
0!
0(
#2775
1!
1(
b1 D
b10 E
#2780
0!
0(
#2785
1!
1(
b10 D
b11 E
#2790
0!
0(
#2795
1!
1(
b11 D
1C
b0 E
1<
#2800
0!
0(
#2805
1!
1(
b1000110 =
b0 D
0C
b1 E
b1000111 >
0<
#2810
0!
0(
#2815
1!
1(
b1 D
b10 E
#2820
0!
0(
#2825
1!
1(
b10 D
b11 E
#2830
0!
0(
#2835
1!
1(
b11 D
1C
b0 E
1<
#2840
0!
0(
#2845
1!
1(
b1000111 =
b0 D
0C
b1 E
b1001000 >
0<
#2850
0!
0(
#2855
1!
1(
b1 D
b10 E
#2860
0!
0(
#2865
1!
1(
b10 D
b11 E
#2870
0!
0(
#2875
1!
1(
b11 D
1C
b0 E
1<
#2880
0!
0(
#2885
1!
1(
b1001000 =
b0 D
0C
b1 E
b1001001 >
0<
#2890
0!
0(
#2895
1!
1(
b1 D
b10 E
#2900
0!
0(
#2905
1!
1(
b10 D
b11 E
#2910
0!
0(
#2915
1!
1(
b11 D
1C
b0 E
1<
#2920
0!
0(
#2925
1!
1(
b1001001 =
b0 D
0C
b1 E
b1001010 >
0<
#2930
0!
0(
#2935
1!
1(
b1 D
b10 E
#2940
0!
0(
#2945
1!
1(
b10 D
b11 E
#2950
0!
0(
#2955
1!
1(
b11 D
1C
b0 E
1<
#2960
0!
0(
#2965
1!
1(
b1001010 =
b0 D
0C
b1 E
b1001011 >
0<
#2970
0!
0(
#2975
1!
1(
b1 D
b10 E
#2980
0!
0(
#2985
1!
1(
b10 D
b11 E
#2990
0!
0(
#2995
1!
1(
b11 D
1C
b0 E
1<
#3000
0!
0(
#3005
1!
1(
b1001011 =
b0 D
0C
b1 E
b1001100 >
0<
#3010
0!
0(
#3015
1!
1(
b1 D
b10 E
#3020
0!
0(
#3025
1!
1(
b10 D
b11 E
#3030
0!
0(
#3035
1!
1(
b11 D
1C
b0 E
1<
#3040
0!
0(
#3045
1!
1(
b1001100 =
b0 D
0C
b1 E
b1001101 >
0<
#3050
0!
0(
#3055
1!
1(
b1 D
b10 E
#3060
0!
0(
#3065
1!
1(
b10 D
b11 E
#3070
0!
0(
#3075
1!
1(
b11 D
1C
b0 E
1<
#3080
0!
0(
#3085
1!
1(
b1001101 =
b0 D
0C
b1 E
b1001110 >
0<
#3090
0!
0(
#3095
1!
1(
b1 D
b10 E
#3100
0!
0(
#3105
1!
1(
b10 D
b11 E
#3110
0!
0(
#3115
1!
1(
b11 D
1C
b0 E
1<
#3120
0!
0(
#3125
1!
1(
b1001110 =
b0 D
0C
b1 E
b1001111 >
0<
#3130
0!
0(
#3135
1!
1(
b1 D
b10 E
#3140
0!
0(
#3145
1!
1(
b10 D
b11 E
#3150
0!
0(
#3155
1!
1(
b11 D
1C
b0 E
1<
#3160
0!
0(
#3165
1!
1(
b1001111 =
b0 D
0C
b1 E
b1010000 >
0<
#3170
0!
0(
#3175
1!
1(
b1 D
b10 E
#3180
0!
0(
#3185
1!
1(
b10 D
b11 E
#3190
0!
0(
#3195
1!
1(
b11 D
1C
b0 E
1<
#3200
0!
0(
#3205
1!
1(
b1010000 =
b0 D
0C
b1 E
b1010001 >
0<
#3210
0!
0(
#3215
1!
1(
b1 D
b10 E
#3220
0!
0(
#3225
1!
1(
b10 D
b11 E
#3230
0!
0(
#3235
1!
1(
b11 D
1C
b0 E
1<
#3240
0!
0(
#3245
1!
1(
b1010001 =
b0 D
0C
b1 E
b1010010 >
0<
#3250
0!
0(
#3255
1!
1(
b1 D
b10 E
#3260
0!
0(
#3265
1!
1(
b10 D
b11 E
#3270
0!
0(
#3275
1!
1(
b11 D
1C
b0 E
1<
#3280
0!
0(
#3285
1!
1(
b1010010 =
b0 D
0C
b1 E
b1010011 >
0<
#3290
0!
0(
#3295
1!
1(
b1 D
b10 E
#3300
0!
0(
#3305
1!
1(
b10 D
b11 E
#3310
0!
0(
#3315
1!
1(
b11 D
1C
b0 E
1<
#3320
0!
0(
#3325
1!
1(
b1010011 =
b0 D
0C
b1 E
b1010100 >
0<
#3330
0!
0(
#3335
1!
1(
b1 D
b10 E
#3340
0!
0(
#3345
1!
1(
b10 D
b11 E
#3350
0!
0(
#3355
1!
1(
b11 D
1C
b0 E
1<
#3360
0!
0(
#3365
1!
1(
b1010100 =
b0 D
0C
b1 E
b1010101 >
0<
#3370
0!
0(
#3375
1!
1(
b1 D
b10 E
#3380
0!
0(
#3385
1!
1(
b10 D
b11 E
#3390
0!
0(
#3395
1!
1(
b11 D
1C
b0 E
1<
#3400
0!
0(
#3405
1!
1(
b1010101 =
b0 D
0C
b1 E
b1010110 >
0<
#3410
0!
0(
#3415
1!
1(
b1 D
b10 E
#3420
0!
0(
#3425
1!
1(
b10 D
b11 E
#3430
0!
0(
#3435
1!
1(
b11 D
1C
b0 E
1<
#3440
0!
0(
